dtit/pyCRCLib/__init__.py
dtit/pyCRCLib/tests/hello.py
dtit/pyCRCLib/tests/test_dtit_crc.py
dtit.pyCRCLib-0.0.2.dist-info/LICENSE
dtit.pyCRCLib-0.0.2.dist-info/METADATA
dtit.pyCRCLib-0.0.2.dist-info/WHEEL
dtit.pyCRCLib-0.0.2.dist-info/top_level.txt
dtit.pyCRCLib-0.0.2.dist-info/RECORD
